<annotation>
  <folder>frame</folder>
  <filename>frame_0030.jpg</filename>
  <source>
    <database>Unknown</database>
    <annotation>Unknown</annotation>
    <image>Unknown</image>
  </source>
  <size>
    <width>1920</width>
    <height>1080</height>
    <depth></depth>
  </size>
  <segmented>0</segmented>
  <object>
    <name>2</name>
    <truncated>0</truncated>
    <occluded>0</occluded>
    <difficult>0</difficult>
    <bndbox>
      <xmin>888.0</xmin>
      <ymin>426.0</ymin>
      <xmax>918.0</xmax>
      <ymax>449.0</ymax>
    </bndbox>
    <attributes>
      <attribute>
        <name>rotation</name>
        <value>0.0</value>
      </attribute>
      <attribute>
        <name>track_id</name>
        <value>3</value>
      </attribute>
      <attribute>
        <name>keyframe</name>
        <value>True</value>
      </attribute>
    </attributes>
  </object>
  <object>
    <name>2</name>
    <truncated>0</truncated>
    <occluded>0</occluded>
    <difficult>0</difficult>
    <bndbox>
      <xmin>849.0</xmin>
      <ymin>459.0</ymin>
      <xmax>886.0</xmax>
      <ymax>489.0</ymax>
    </bndbox>
    <attributes>
      <attribute>
        <name>rotation</name>
        <value>0.0</value>
      </attribute>
      <attribute>
        <name>track_id</name>
        <value>13</value>
      </attribute>
      <attribute>
        <name>keyframe</name>
        <value>True</value>
      </attribute>
    </attributes>
  </object>
  <object>
    <name>7</name>
    <truncated>0</truncated>
    <occluded>0</occluded>
    <difficult>0</difficult>
    <bndbox>
      <xmin>634.8</xmin>
      <ymin>469.46</ymin>
      <xmax>704.8</xmax>
      <ymax>538.46</ymax>
    </bndbox>
    <attributes>
      <attribute>
        <name>rotation</name>
        <value>0.0</value>
      </attribute>
      <attribute>
        <name>track_id</name>
        <value>15</value>
      </attribute>
      <attribute>
        <name>keyframe</name>
        <value>True</value>
      </attribute>
    </attributes>
  </object>
  <object>
    <name>7</name>
    <truncated>0</truncated>
    <occluded>0</occluded>
    <difficult>0</difficult>
    <bndbox>
      <xmin>728.0</xmin>
      <ymin>447.0</ymin>
      <xmax>797.0</xmax>
      <ymax>524.0</ymax>
    </bndbox>
    <attributes>
      <attribute>
        <name>rotation</name>
        <value>0.0</value>
      </attribute>
      <attribute>
        <name>track_id</name>
        <value>16</value>
      </attribute>
      <attribute>
        <name>keyframe</name>
        <value>True</value>
      </attribute>
    </attributes>
  </object>
  <object>
    <name>2</name>
    <truncated>0</truncated>
    <occluded>0</occluded>
    <difficult>0</difficult>
    <bndbox>
      <xmin>832.0</xmin>
      <ymin>487.0</ymin>
      <xmax>881.0</xmax>
      <ymax>523.0</ymax>
    </bndbox>
    <attributes>
      <attribute>
        <name>rotation</name>
        <value>0.0</value>
      </attribute>
      <attribute>
        <name>track_id</name>
        <value>17</value>
      </attribute>
      <attribute>
        <name>keyframe</name>
        <value>True</value>
      </attribute>
    </attributes>
  </object>
  <object>
    <name>2</name>
    <truncated>0</truncated>
    <occluded>0</occluded>
    <difficult>0</difficult>
    <bndbox>
      <xmin>794.0</xmin>
      <ymin>533.0</ymin>
      <xmax>855.0</xmax>
      <ymax>585.0</ymax>
    </bndbox>
    <attributes>
      <attribute>
        <name>rotation</name>
        <value>0.0</value>
      </attribute>
      <attribute>
        <name>track_id</name>
        <value>19</value>
      </attribute>
      <attribute>
        <name>keyframe</name>
        <value>True</value>
      </attribute>
    </attributes>
  </object>
  <object>
    <name>2</name>
    <truncated>0</truncated>
    <occluded>0</occluded>
    <difficult>0</difficult>
    <bndbox>
      <xmin>1295.8</xmin>
      <ymin>560.2</ymin>
      <xmax>1395.4</xmax>
      <ymax>628.19</ymax>
    </bndbox>
    <attributes>
      <attribute>
        <name>rotation</name>
        <value>0.0</value>
      </attribute>
      <attribute>
        <name>track_id</name>
        <value>20</value>
      </attribute>
      <attribute>
        <name>keyframe</name>
        <value>True</value>
      </attribute>
    </attributes>
  </object>
  <object>
    <name>2</name>
    <truncated>0</truncated>
    <occluded>0</occluded>
    <difficult>0</difficult>
    <bndbox>
      <xmin>634.0</xmin>
      <ymin>565.0</ymin>
      <xmax>712.0</xmax>
      <ymax>625.0</ymax>
    </bndbox>
    <attributes>
      <attribute>
        <name>rotation</name>
        <value>0.0</value>
      </attribute>
      <attribute>
        <name>track_id</name>
        <value>21</value>
      </attribute>
      <attribute>
        <name>keyframe</name>
        <value>True</value>
      </attribute>
    </attributes>
  </object>
  <object>
    <name>7</name>
    <truncated>0</truncated>
    <occluded>0</occluded>
    <difficult>0</difficult>
    <bndbox>
      <xmin>704.0</xmin>
      <ymin>624.0</ymin>
      <xmax>801.0</xmax>
      <ymax>719.0</ymax>
    </bndbox>
    <attributes>
      <attribute>
        <name>rotation</name>
        <value>0.0</value>
      </attribute>
      <attribute>
        <name>track_id</name>
        <value>22</value>
      </attribute>
      <attribute>
        <name>keyframe</name>
        <value>True</value>
      </attribute>
    </attributes>
  </object>
</annotation>
