<annotation>
  <folder>frame</folder>
  <filename>frame_0295.jpg</filename>
  <source>
    <database>Unknown</database>
    <annotation>Unknown</annotation>
    <image>Unknown</image>
  </source>
  <size>
    <width>1920</width>
    <height>1080</height>
    <depth></depth>
  </size>
  <segmented>0</segmented>
  <object>
    <name>7</name>
    <truncated>0</truncated>
    <occluded>0</occluded>
    <difficult>0</difficult>
    <bndbox>
      <xmin>792.95</xmin>
      <ymin>436.4</ymin>
      <xmax>838.4</xmax>
      <ymax>473.5</ymax>
    </bndbox>
    <attributes>
      <attribute>
        <name>rotation</name>
        <value>0.0</value>
      </attribute>
      <attribute>
        <name>track_id</name>
        <value>125</value>
      </attribute>
      <attribute>
        <name>keyframe</name>
        <value>False</value>
      </attribute>
    </attributes>
  </object>
  <object>
    <name>2</name>
    <truncated>0</truncated>
    <occluded>0</occluded>
    <difficult>0</difficult>
    <bndbox>
      <xmin>864.0</xmin>
      <ymin>442.0</ymin>
      <xmax>901.0</xmax>
      <ymax>476.0</ymax>
    </bndbox>
    <attributes>
      <attribute>
        <name>rotation</name>
        <value>0.0</value>
      </attribute>
      <attribute>
        <name>track_id</name>
        <value>126</value>
      </attribute>
      <attribute>
        <name>keyframe</name>
        <value>True</value>
      </attribute>
    </attributes>
  </object>
  <object>
    <name>2</name>
    <truncated>0</truncated>
    <occluded>0</occluded>
    <difficult>0</difficult>
    <bndbox>
      <xmin>761.0</xmin>
      <ymin>472.0</ymin>
      <xmax>807.0</xmax>
      <ymax>506.0</ymax>
    </bndbox>
    <attributes>
      <attribute>
        <name>rotation</name>
        <value>0.0</value>
      </attribute>
      <attribute>
        <name>track_id</name>
        <value>128</value>
      </attribute>
      <attribute>
        <name>keyframe</name>
        <value>True</value>
      </attribute>
    </attributes>
  </object>
  <object>
    <name>2</name>
    <truncated>0</truncated>
    <occluded>0</occluded>
    <difficult>0</difficult>
    <bndbox>
      <xmin>1442.7</xmin>
      <ymin>645.2</ymin>
      <xmax>1570.74</xmax>
      <ymax>738.67</ymax>
    </bndbox>
    <attributes>
      <attribute>
        <name>rotation</name>
        <value>0.0</value>
      </attribute>
      <attribute>
        <name>track_id</name>
        <value>130</value>
      </attribute>
      <attribute>
        <name>keyframe</name>
        <value>True</value>
      </attribute>
    </attributes>
  </object>
  <object>
    <name>2</name>
    <truncated>0</truncated>
    <occluded>0</occluded>
    <difficult>0</difficult>
    <bndbox>
      <xmin>704.0</xmin>
      <ymin>531.0</ymin>
      <xmax>749.0</xmax>
      <ymax>580.0</ymax>
    </bndbox>
    <attributes>
      <attribute>
        <name>rotation</name>
        <value>0.0</value>
      </attribute>
      <attribute>
        <name>track_id</name>
        <value>132</value>
      </attribute>
      <attribute>
        <name>keyframe</name>
        <value>True</value>
      </attribute>
    </attributes>
  </object>
  <object>
    <name>2</name>
    <truncated>0</truncated>
    <occluded>0</occluded>
    <difficult>0</difficult>
    <bndbox>
      <xmin>1029.0</xmin>
      <ymin>468.0</ymin>
      <xmax>1072.0</xmax>
      <ymax>504.0</ymax>
    </bndbox>
    <attributes>
      <attribute>
        <name>rotation</name>
        <value>0.0</value>
      </attribute>
      <attribute>
        <name>track_id</name>
        <value>133</value>
      </attribute>
      <attribute>
        <name>keyframe</name>
        <value>True</value>
      </attribute>
    </attributes>
  </object>
  <object>
    <name>2</name>
    <truncated>0</truncated>
    <occluded>0</occluded>
    <difficult>0</difficult>
    <bndbox>
      <xmin>739.0</xmin>
      <ymin>618.0</ymin>
      <xmax>830.0</xmax>
      <ymax>690.0</ymax>
    </bndbox>
    <attributes>
      <attribute>
        <name>rotation</name>
        <value>0.0</value>
      </attribute>
      <attribute>
        <name>track_id</name>
        <value>134</value>
      </attribute>
      <attribute>
        <name>keyframe</name>
        <value>True</value>
      </attribute>
    </attributes>
  </object>
  <object>
    <name>2</name>
    <truncated>0</truncated>
    <occluded>0</occluded>
    <difficult>0</difficult>
    <bndbox>
      <xmin>1075.0</xmin>
      <ymin>446.0</ymin>
      <xmax>1113.0</xmax>
      <ymax>476.0</ymax>
    </bndbox>
    <attributes>
      <attribute>
        <name>rotation</name>
        <value>0.0</value>
      </attribute>
      <attribute>
        <name>track_id</name>
        <value>135</value>
      </attribute>
      <attribute>
        <name>keyframe</name>
        <value>True</value>
      </attribute>
    </attributes>
  </object>
  <object>
    <name>7</name>
    <truncated>0</truncated>
    <occluded>0</occluded>
    <difficult>0</difficult>
    <bndbox>
      <xmin>412.0</xmin>
      <ymin>484.0</ymin>
      <xmax>713.0</xmax>
      <ymax>772.0</ymax>
    </bndbox>
    <attributes>
      <attribute>
        <name>rotation</name>
        <value>0.0</value>
      </attribute>
      <attribute>
        <name>track_id</name>
        <value>136</value>
      </attribute>
      <attribute>
        <name>keyframe</name>
        <value>True</value>
      </attribute>
    </attributes>
  </object>
  <object>
    <name>7</name>
    <truncated>0</truncated>
    <occluded>0</occluded>
    <difficult>0</difficult>
    <bndbox>
      <xmin>372.0</xmin>
      <ymin>498.0</ymin>
      <xmax>560.0</xmax>
      <ymax>676.0</ymax>
    </bndbox>
    <attributes>
      <attribute>
        <name>rotation</name>
        <value>0.0</value>
      </attribute>
      <attribute>
        <name>track_id</name>
        <value>137</value>
      </attribute>
      <attribute>
        <name>keyframe</name>
        <value>True</value>
      </attribute>
    </attributes>
  </object>
  <object>
    <name>2</name>
    <truncated>0</truncated>
    <occluded>0</occluded>
    <difficult>0</difficult>
    <bndbox>
      <xmin>1202.1</xmin>
      <ymin>488.7</ymin>
      <xmax>1263.44</xmax>
      <ymax>548.33</ymax>
    </bndbox>
    <attributes>
      <attribute>
        <name>rotation</name>
        <value>0.0</value>
      </attribute>
      <attribute>
        <name>track_id</name>
        <value>154</value>
      </attribute>
      <attribute>
        <name>keyframe</name>
        <value>True</value>
      </attribute>
    </attributes>
  </object>
</annotation>
