<annotation>
  <folder>frame</folder>
  <filename>frame_0292.jpg</filename>
  <source>
    <database>Unknown</database>
    <annotation>Unknown</annotation>
    <image>Unknown</image>
  </source>
  <size>
    <width>1920</width>
    <height>1080</height>
    <depth></depth>
  </size>
  <segmented>0</segmented>
  <object>
    <name>2</name>
    <truncated>0</truncated>
    <occluded>0</occluded>
    <difficult>0</difficult>
    <bndbox>
      <xmin>830.0</xmin>
      <ymin>426.0</ymin>
      <xmax>865.0</xmax>
      <ymax>450.0</ymax>
    </bndbox>
    <attributes>
      <attribute>
        <name>rotation</name>
        <value>0.0</value>
      </attribute>
      <attribute>
        <name>track_id</name>
        <value>117</value>
      </attribute>
      <attribute>
        <name>keyframe</name>
        <value>True</value>
      </attribute>
    </attributes>
  </object>
  <object>
    <name>7</name>
    <truncated>0</truncated>
    <occluded>0</occluded>
    <difficult>0</difficult>
    <bndbox>
      <xmin>779.88</xmin>
      <ymin>440.46</ymin>
      <xmax>831.88</xmax>
      <ymax>485.76</ymax>
    </bndbox>
    <attributes>
      <attribute>
        <name>rotation</name>
        <value>0.0</value>
      </attribute>
      <attribute>
        <name>track_id</name>
        <value>125</value>
      </attribute>
      <attribute>
        <name>keyframe</name>
        <value>True</value>
      </attribute>
    </attributes>
  </object>
  <object>
    <name>2</name>
    <truncated>0</truncated>
    <occluded>0</occluded>
    <difficult>0</difficult>
    <bndbox>
      <xmin>858.0</xmin>
      <ymin>448.0</ymin>
      <xmax>899.0</xmax>
      <ymax>486.0</ymax>
    </bndbox>
    <attributes>
      <attribute>
        <name>rotation</name>
        <value>0.0</value>
      </attribute>
      <attribute>
        <name>track_id</name>
        <value>126</value>
      </attribute>
      <attribute>
        <name>keyframe</name>
        <value>True</value>
      </attribute>
    </attributes>
  </object>
  <object>
    <name>2</name>
    <truncated>0</truncated>
    <occluded>0</occluded>
    <difficult>0</difficult>
    <bndbox>
      <xmin>739.0</xmin>
      <ymin>483.0</ymin>
      <xmax>796.0</xmax>
      <ymax>521.0</ymax>
    </bndbox>
    <attributes>
      <attribute>
        <name>rotation</name>
        <value>0.0</value>
      </attribute>
      <attribute>
        <name>track_id</name>
        <value>128</value>
      </attribute>
      <attribute>
        <name>keyframe</name>
        <value>True</value>
      </attribute>
    </attributes>
  </object>
  <object>
    <name>2</name>
    <truncated>0</truncated>
    <occluded>0</occluded>
    <difficult>0</difficult>
    <bndbox>
      <xmin>1298.6</xmin>
      <ymin>552.5</ymin>
      <xmax>1380.09</xmax>
      <ymax>614.43</ymax>
    </bndbox>
    <attributes>
      <attribute>
        <name>rotation</name>
        <value>0.0</value>
      </attribute>
      <attribute>
        <name>track_id</name>
        <value>130</value>
      </attribute>
      <attribute>
        <name>keyframe</name>
        <value>True</value>
      </attribute>
    </attributes>
  </object>
  <object>
    <name>2</name>
    <truncated>0</truncated>
    <occluded>0</occluded>
    <difficult>0</difficult>
    <bndbox>
      <xmin>1326.9</xmin>
      <ymin>682.9</ymin>
      <xmax>1457.25</xmax>
      <ymax>788.36</ymax>
    </bndbox>
    <attributes>
      <attribute>
        <name>rotation</name>
        <value>0.0</value>
      </attribute>
      <attribute>
        <name>track_id</name>
        <value>131</value>
      </attribute>
      <attribute>
        <name>keyframe</name>
        <value>True</value>
      </attribute>
    </attributes>
  </object>
  <object>
    <name>2</name>
    <truncated>0</truncated>
    <occluded>0</occluded>
    <difficult>0</difficult>
    <bndbox>
      <xmin>666.0</xmin>
      <ymin>554.0</ymin>
      <xmax>728.0</xmax>
      <ymax>610.0</ymax>
    </bndbox>
    <attributes>
      <attribute>
        <name>rotation</name>
        <value>0.0</value>
      </attribute>
      <attribute>
        <name>track_id</name>
        <value>132</value>
      </attribute>
      <attribute>
        <name>keyframe</name>
        <value>True</value>
      </attribute>
    </attributes>
  </object>
  <object>
    <name>2</name>
    <truncated>0</truncated>
    <occluded>0</occluded>
    <difficult>0</difficult>
    <bndbox>
      <xmin>1016.0</xmin>
      <ymin>447.0</ymin>
      <xmax>1055.0</xmax>
      <ymax>477.0</ymax>
    </bndbox>
    <attributes>
      <attribute>
        <name>rotation</name>
        <value>0.0</value>
      </attribute>
      <attribute>
        <name>track_id</name>
        <value>133</value>
      </attribute>
      <attribute>
        <name>keyframe</name>
        <value>True</value>
      </attribute>
    </attributes>
  </object>
  <object>
    <name>2</name>
    <truncated>0</truncated>
    <occluded>0</occluded>
    <difficult>0</difficult>
    <bndbox>
      <xmin>700.0</xmin>
      <ymin>667.0</ymin>
      <xmax>809.0</xmax>
      <ymax>758.0</ymax>
    </bndbox>
    <attributes>
      <attribute>
        <name>rotation</name>
        <value>0.0</value>
      </attribute>
      <attribute>
        <name>track_id</name>
        <value>134</value>
      </attribute>
      <attribute>
        <name>keyframe</name>
        <value>True</value>
      </attribute>
    </attributes>
  </object>
  <object>
    <name>2</name>
    <truncated>0</truncated>
    <occluded>0</occluded>
    <difficult>0</difficult>
    <bndbox>
      <xmin>1157.29</xmin>
      <ymin>460.46</ymin>
      <xmax>1203.75</xmax>
      <ymax>505.22</ymax>
    </bndbox>
    <attributes>
      <attribute>
        <name>rotation</name>
        <value>0.0</value>
      </attribute>
      <attribute>
        <name>track_id</name>
        <value>154</value>
      </attribute>
      <attribute>
        <name>keyframe</name>
        <value>True</value>
      </attribute>
    </attributes>
  </object>
</annotation>
